stats.cpython-38-x86_64-linux-gnu.so
slurp/__init__.py
slurp/masks/__init__.py
slurp/masks/shadowmask.py
slurp/masks/stack_masks.py
slurp/masks/urbanmask.py
slurp/masks/vegetationmask.py
slurp/masks/watermask.py
slurp/post_process/__init__.py
slurp/post_process/morphology.py
slurp/prepare/__init__.py
slurp/prepare/analyse_glcm.py
slurp/prepare/aux_files.py
slurp/prepare/geometry.py
slurp/prepare/prepare.py
slurp/prepare/primitives.py
slurp/prepare/validity.py
slurp/stats/cysrc/__init__.py
slurp/stats/cysrc/c_stats.cpp
slurp/stats/cysrc/c_stats.h
slurp/stats/cysrc/stats.cpp
slurp/stats/cysrc/stats.pyx
slurp/tools/__init__.py
slurp/tools/constant.py
slurp/tools/eoscale_utils.py
slurp/tools/io_utils.py
slurp/tools/misc.py
slurp/tools/mylogger.py
slurp/tools/pydantic_class.py
slurp/tools/random_forest_utils.py
slurp/tools/utils.py
slurp/tools/logs/__init__.py
slurp/tools/logs/out2json.json
slurp/tools/logs/out2stdout.json
slurp_masks-0.0.2.dist-info/LICENSE
slurp_masks-0.0.2.dist-info/METADATA
slurp_masks-0.0.2.dist-info/WHEEL
slurp_masks-0.0.2.dist-info/entry_points.txt
slurp_masks-0.0.2.dist-info/top_level.txt
slurp_masks-0.0.2.dist-info/RECORD
