Metadata-Version: 2.1
Name: slurp-masks
Version: 0.0.2
Summary: Smart Land Use Reconstruction Pipeline
Home-page: https://github.com/CNES/slurp
Author: Yannick TANGUY
Author-email: yannick.tanguy@cnes.fr
Keywords: slurp,LULC,mask,segmentation,classification
Platform: any
Classifier: Development Status :: 4 - Beta
Classifier: Intended Audience :: Developers
Classifier: Intended Audience :: End Users/Desktop
Classifier: Intended Audience :: Science/Research
Classifier: Environment :: Console
Classifier: Topic :: Software Development :: Libraries :: Python Modules
Classifier: Operating System :: OS Independent
Classifier: Natural Language :: English
Classifier: Programming Language :: Python
Classifier: Programming Language :: Python :: 3
Classifier: Programming Language :: Python :: 3.8
Classifier: Programming Language :: Cython
Requires-Python: >=3.8
License-File: LICENSE
Requires-Dist: argparse
Requires-Dist: argcomplete
Requires-Dist: eoscale
Requires-Dist: rasterio
Requires-Dist: scikit-image
Requires-Dist: scikit-learn
Requires-Dist: shareloc
Requires-Dist: geopandas
Requires-Dist: scikit-learn-intelex
Requires-Dist: matplotlib
Requires-Dist: Cython
Requires-Dist: pydantic
Requires-Dist: psutil
Provides-Extra: dev
Requires-Dist: pre-commit; extra == "dev"
Requires-Dist: isort>=5.8.0; extra == "dev"
Requires-Dist: black>=21.5b0; extra == "dev"
Requires-Dist: flake8>=3.9.1; extra == "dev"
Requires-Dist: flake8-comprehensions>=3.4.0; extra == "dev"
Requires-Dist: flake8-bugbear>=21.4.3; extra == "dev"
Requires-Dist: pylint; extra == "dev"
Requires-Dist: setuptools-scm; extra == "dev"
Requires-Dist: virtualenv; extra == "dev"
Requires-Dist: configupdater; extra == "dev"
Requires-Dist: twine; extra == "dev"
Requires-Dist: pytest; extra == "dev"
Requires-Dist: pytest-cov; extra == "dev"
Requires-Dist: pygments; extra == "dev"
Requires-Dist: tox; extra == "dev"
Provides-Extra: docs
Requires-Dist: sphinx; extra == "docs"
Requires-Dist: sphinx-rtd-theme; extra == "docs"
Requires-Dist: sphinx-autoapi; extra == "docs"
